django_cog/__init__.py
django_cog/admin.py
django_cog/apps.py
django_cog/celery.py
django_cog/models.py
django_cog/tests.py
django_cog/migrations/0001_initial.py
django_cog/migrations/0002_pipelinerun_arguments_as_json.py
django_cog/migrations/__init__.py
django_cog/templates/cancel_run.html
django_cog/templates/change_form.html
django_cog-1.4.1.dist-info/METADATA
django_cog-1.4.1.dist-info/WHEEL
django_cog-1.4.1.dist-info/top_level.txt
django_cog-1.4.1.dist-info/RECORD
