Metadata-Version: 2.4
Name: django-cog
Version: 1.4.1
Summary: Django library for launching pipelines of multiple stages and parallel tasks.
Home-page: https://github.com/david-pettifor-nd/django_cog.git
Author: David W Pettifor
Author-email: dpettifo@nd.edu
License: MIT
Classifier: License :: OSI Approved :: MIT License
Classifier: Programming Language :: Python :: 3
Classifier: Programming Language :: Python :: 3.12
Classifier: Framework :: Django :: 2.2
Classifier: Framework :: Django :: 3.2
Classifier: Framework :: Django :: 4.1
Classifier: Framework :: Django :: 5.2
Requires-Dist: celery==5.5.2
Requires-Dist: django-celery-beat==2.8.1
Requires-Dist: django-nested-inline>=0.4.6
Dynamic: author
Dynamic: author-email
Dynamic: classifier
Dynamic: description
Dynamic: description-content-type
Dynamic: home-page
Dynamic: license
Dynamic: requires-dist
Dynamic: summary
